jnumpy/__init__.py
jnumpy/apis.py
jnumpy/defaults.py
jnumpy/envars.py
jnumpy/init.py
jnumpy/InitTools.jl
jnumpy/JNumPyEnv/Project.toml
jnumpy/JNumPyEnv/README.md
jnumpy/tests/__init__.py
jnumpy/tests/extension/__init__.py
jnumpy/tests/extension/__init__.pyi
jnumpy/tests/extension/Project.toml
jnumpy/tests/extension/src/extension.jl
jnumpy/tests/test_core.py
jnumpy/tests/test_fast_init.py
jnumpy/TyPython/Project.toml
jnumpy/TyPython/src/C.jl
jnumpy/TyPython/src/CPython.APIs.jl
jnumpy/TyPython/src/CPython.Boot.jl
jnumpy/TyPython/src/CPython.Defs.jl
jnumpy/TyPython/src/CPython.Dev.DevOnly.compiled.jl
jnumpy/TyPython/src/CPython.Dev.DevOnly.jl
jnumpy/TyPython/src/CPython.Dev.jl
jnumpy/TyPython/src/CPython.jl
jnumpy/TyPython/src/CPython.Julia.jl
jnumpy/TyPython/src/CPython.NumPy.DevOnly.compiled.jl
jnumpy/TyPython/src/CPython.NumPy.DevOnly.jl
jnumpy/TyPython/src/CPython.NumPy.jl
jnumpy/TyPython/src/CPython.ORM.jl
jnumpy/TyPython/src/DevOnly.jl
jnumpy/TyPython/src/Reflection.DevOnly.compiled.jl
jnumpy/TyPython/src/Reflection.DevOnly.jl
jnumpy/TyPython/src/Reflection.jl
jnumpy/TyPython/src/TyPython.jl
jnumpy/TyPython/src/Utils.DevOnly.compiled.jl
jnumpy/TyPython/src/Utils.DevOnly.jl
jnumpy/TyPython/src/Utils.jl
jnumpy/utils.py
julia_numpy-0.4.9.dist-info/LICENSE
julia_numpy-0.4.9.dist-info/METADATA
julia_numpy-0.4.9.dist-info/WHEEL
julia_numpy-0.4.9.dist-info/RECORD
