Metadata-Version: 2.1
Name: julia-numpy
Version: 0.4.9
Summary: Writing Python C extensions in Julia within 5 minutes.
Home-page: https://github.com/Suzhou-Tongyuan/jnumpy
License: MIT
Author: thautwarm
Author-email: twshere@outlook.com
Maintainer: songjhaha
Maintainer-email: songjh96@foxmail.com
Requires-Python: >=3.7,<4.0
Classifier: License :: OSI Approved :: MIT License
Classifier: Programming Language :: Python :: 3
Classifier: Programming Language :: Python :: 3.7
Classifier: Programming Language :: Python :: 3.8
Classifier: Programming Language :: Python :: 3.9
Classifier: Programming Language :: Python :: 3.10
Classifier: Programming Language :: Python :: 3.11
Requires-Dist: numpy (>=1.18,<2.0)
Requires-Dist: tomli (>=2.0.1,<3.0.0)
